sqlalchemy_jdbcapi/__init__.py
sqlalchemy_jdbcapi/py.typed
sqlalchemy_jdbcapi/dialects/__init__.py
sqlalchemy_jdbcapi/dialects/base.py
sqlalchemy_jdbcapi/dialects/db2.py
sqlalchemy_jdbcapi/dialects/mssql.py
sqlalchemy_jdbcapi/dialects/mysql.py
sqlalchemy_jdbcapi/dialects/oceanbase.py
sqlalchemy_jdbcapi/dialects/odbc_base.py
sqlalchemy_jdbcapi/dialects/odbc_mssql.py
sqlalchemy_jdbcapi/dialects/odbc_mysql.py
sqlalchemy_jdbcapi/dialects/odbc_oracle.py
sqlalchemy_jdbcapi/dialects/odbc_postgresql.py
sqlalchemy_jdbcapi/dialects/oracle.py
sqlalchemy_jdbcapi/dialects/postgresql.py
sqlalchemy_jdbcapi/dialects/sqlite.py
sqlalchemy_jdbcapi/jdbc/__init__.py
sqlalchemy_jdbcapi/jdbc/connection.py
sqlalchemy_jdbcapi/jdbc/cursor.py
sqlalchemy_jdbcapi/jdbc/dataframe.py
sqlalchemy_jdbcapi/jdbc/driver_manager.py
sqlalchemy_jdbcapi/jdbc/exceptions.py
sqlalchemy_jdbcapi/jdbc/jvm.py
sqlalchemy_jdbcapi/jdbc/type_converter.py
sqlalchemy_jdbcapi/jdbc/types.py
sqlalchemy_jdbcapi/odbc/__init__.py
sqlalchemy_jdbcapi/odbc/connection.py
sqlalchemy_jdbcapi/odbc/exceptions.py
sqlalchemy_jdbcapi-2.1.3.dist-info/licenses/AUTHORS
sqlalchemy_jdbcapi-2.1.3.dist-info/licenses/LICENSE
sqlalchemy_jdbcapi-2.1.3.dist-info/METADATA
sqlalchemy_jdbcapi-2.1.3.dist-info/WHEEL
sqlalchemy_jdbcapi-2.1.3.dist-info/entry_points.txt
sqlalchemy_jdbcapi-2.1.3.dist-info/top_level.txt
sqlalchemy_jdbcapi-2.1.3.dist-info/RECORD
