Metadata-Version: 2.4
Name: sqlalchemy-jdbcapi
Version: 2.1.3
Summary: Modern SQLAlchemy dialect for JDBC connections with native implementation
Author: Pavel Henrykhsen
Author-email: Danesh Patel <danesh_patel@outlook.com>
Maintainer-email: Danesh Patel <danesh_patel@outlook.com>
License: Apache-2.0
Project-URL: Homepage, https://github.com/daneshpatel/sqlalchemy-jdbcapi
Project-URL: Documentation, https://sqlalchemy-jdbcapi.readthedocs.io
Project-URL: Repository, https://github.com/daneshpatel/sqlalchemy-jdbcapi
Project-URL: Issues, https://github.com/daneshpatel/sqlalchemy-jdbcapi/issues
Project-URL: Changelog, https://github.com/daneshpatel/sqlalchemy-jdbcapi/blob/main/CHANGELOG.md
Keywords: sqlalchemy,jdbc,database,postgresql,oracle,mysql,sql-server,db2,oceanbase
Classifier: Development Status :: 4 - Beta
Classifier: Intended Audience :: Developers
Classifier: License :: OSI Approved :: Apache Software License
Classifier: Operating System :: OS Independent
Classifier: Programming Language :: Python :: 3
Classifier: Programming Language :: Python :: 3.10
Classifier: Programming Language :: Python :: 3.11
Classifier: Programming Language :: Python :: 3.12
Classifier: Programming Language :: Python :: 3.13
Classifier: Programming Language :: Python :: Implementation :: CPython
Classifier: Topic :: Database
Classifier: Topic :: Database :: Front-Ends
Classifier: Topic :: Software Development :: Libraries :: Python Modules
Classifier: Typing :: Typed
Requires-Python: >=3.10
License-File: LICENSE
License-File: AUTHORS
Requires-Dist: sqlalchemy>=2.0.0
Requires-Dist: JPype1>=1.5.0
Provides-Extra: odbc
Requires-Dist: pyodbc>=5.0.0; extra == "odbc"
Provides-Extra: dataframe
Requires-Dist: pandas>=2.0.0; extra == "dataframe"
Requires-Dist: polars>=0.20.0; extra == "dataframe"
Requires-Dist: pyarrow>=14.0.0; extra == "dataframe"
Provides-Extra: dev
Requires-Dist: pytest>=8.0.0; extra == "dev"
Requires-Dist: pytest-cov>=4.1.0; extra == "dev"
Requires-Dist: pytest-mock>=3.12.0; extra == "dev"
Requires-Dist: pytest-asyncio>=0.23.0; extra == "dev"
Requires-Dist: pytest-xdist>=3.5.0; extra == "dev"
Requires-Dist: mypy>=1.8.0; extra == "dev"
Requires-Dist: ruff>=0.2.0; extra == "dev"
Requires-Dist: pre-commit>=3.6.0; extra == "dev"
Requires-Dist: tox>=4.11.0; extra == "dev"
Requires-Dist: build>=1.0.0; extra == "dev"
Requires-Dist: twine>=5.0.0; extra == "dev"
Requires-Dist: bump2version>=1.0.1; extra == "dev"
Provides-Extra: docs
Requires-Dist: sphinx>=7.2.0; extra == "docs"
Requires-Dist: furo>=2024.1.29; extra == "docs"
Requires-Dist: sphinx-autodoc-typehints>=1.25.0; extra == "docs"
Requires-Dist: sphinx-copybutton>=0.5.2; extra == "docs"
Requires-Dist: myst-parser>=2.0.0; extra == "docs"
Provides-Extra: types
Requires-Dist: types-python-dateutil; extra == "types"
Provides-Extra: all
Requires-Dist: sqlalchemy-jdbcapi[dataframe,dev,docs,odbc,types]; extra == "all"
Dynamic: license-file
